linkedin_posts/__init__.py
linkedin_posts/comments.py
linkedin_posts/constants.py
linkedin_posts/exceptions.py
linkedin_posts/formats.py
linkedin_posts/headers.py
linkedin_posts/images.py
linkedin_posts/polls.py
linkedin_posts/posts.py
linkedin_posts/tokens.py
linkedin_posts-0.0.12.dist-info/LICENSE
linkedin_posts-0.0.12.dist-info/METADATA
linkedin_posts-0.0.12.dist-info/WHEEL
linkedin_posts-0.0.12.dist-info/top_level.txt
linkedin_posts-0.0.12.dist-info/RECORD
