Metadata-Version: 2.1
Name: linkedin-posts
Version: 0.0.12
Summary: Utility to share Linkedin posts using the Linkedin Marketing API
Author-email: Rami <ramiboutas@protonmail.com>
Project-URL: Homepage, https://github.com/ramiboutas/linkedin-posts
Project-URL: Bug Tracker, https://github.com/ramiboutas/linkedin-posts/issues
Classifier: Development Status :: 4 - Beta
Classifier: Programming Language :: Python :: 3
Classifier: License :: OSI Approved :: MIT License
Classifier: Operating System :: OS Independent
Classifier: Intended Audience :: Developers
Requires-Python: >=3.7
License-File: LICENSE
Requires-Dist: requests
